split_cosine_utils/__init__.py
split_cosine_utils/main.py
split_cosine_utils-0.6.0.dist-info/METADATA
split_cosine_utils-0.6.0.dist-info/WHEEL
split_cosine_utils-0.6.0.dist-info/entry_points.txt
split_cosine_utils-0.6.0.dist-info/top_level.txt
split_cosine_utils-0.6.0.dist-info/RECORD
