Metadata-Version: 2.1
Name: split-cosine-utils
Version: 0.6.0
Summary: A utility package for data splitting and cosine similarity computations. With an emphasis on dataframe manipulation
Author: Alfonso Esqueda
Author-email: alfonso.esqueda.kc@gmail.com
Classifier: Programming Language :: Python :: 3
Classifier: License :: OSI Approved :: MIT License
Classifier: Operating System :: OS Independent
Requires-Python: >=3.6
Requires-Dist: pandas
Requires-Dist: scikit-learn
